{
  "review_id": "P1-IMPLEMENT-09-REVIEW-001",
  "workpack_id": "P1-IMPLEMENT-09-THIN-CLI-TEMPLATES-DOCS",
  "subject_hash": "2680e2fbcfca13abd2a9fb2398b1e9bc0a013d6d2d7a6dc128bd957ffe216c05",
  "decision": "APPROVED",
  "reviewer": "HUMAN_GATE",
  "approved_sections": [
    "WORKPACK_EXECUTION_RESULT.json",
    "SCOPE_REPORT.json",
    "TEST_REPORT.json",
    "CANDIDATE_MANIFEST.json",
    "PART_SELF_CHECK.md",
    "HANDOFF.md"
  ],
  "approved_scope": [
    "repository/src/drd_harness/cli/**",
    "repository/src/drd_harness/kernel/import_boundaries.py",
    "repository/templates/**",
    "repository/docs/**",
    "repository/tests/integration/**",
    "repository/tests/kernel/test_import_boundaries.py"
  ],
  "open_blockers": [],
  "notes": [
    "Approved after repair of CLI structured failure handling, candidate hash ordering, runtime boundary false positives, and static import coverage.",
    "This approval does not create BUILD_LOCK or promotion authority."
  ]
}
